{"id":77666,"name":"PractiFinder","description":"Desarrolo de Applicaciones Open Source","revision":3,"lastModifiedDate":"2023-09-13T21:42:49Z","lastModifiedUser":"u202123714@upc.edu.pe","lastModifiedAgent":"structurizr-cloud/diagram-editor/68e41e7f-7a13-48aa-8557-b280dcbf332f","model":{"people":[{"id":"7","tags":"Element,Person,Doctor","name":"Employer","description":"Employer User","relationships":[{"id":"28","tags":"Relationship","sourceId":"7","destinationId":"16","description":"Consult"},{"id":"10","tags":"Relationship","sourceId":"7","destinationId":"1","description":"Users who offer jobs."},{"id":"29","tags":"Relationship","sourceId":"7","destinationId":"17","description":"Consult"}],"location":"Unspecified"},{"id":"8","tags":"Element,Person,Admin","name":"Admin","description":"User Admin.","relationships":[{"id":"26","tags":"Relationship","sourceId":"8","destinationId":"16","description":"Consult"},{"id":"11","tags":"Relationship","sourceId":"8","destinationId":"1","description":"Validates the registration of users to the system and updates the information of the app."},{"id":"27","tags":"Relationship","sourceId":"8","destinationId":"17","description":"Consult"}],"location":"Unspecified"},{"id":"6","tags":"Element,Person,Paciente","name":"Student","description":"Student User","relationships":[{"id":"25","tags":"Relationship","sourceId":"6","destinationId":"17","description":"Consult"},{"id":"9","tags":"Relationship","sourceId":"6","destinationId":"1","description":"Users seeking internships or work experience."},{"id":"24","tags":"Relationship","sourceId":"6","destinationId":"16","description":"Consult"}],"location":"Unspecified"}],"softwareSystems":[{"id":"5","tags":"Element,Software System,DeliverySystem","name":"Google Firebase System","description":"Allows users to register, log in, recover and change password and authenticate credentials","location":"Unspecified","documentation":{}},{"id":"4","tags":"Element,Software System,Mastercard","name":"Zoom System","description":"Allows users to generates and participate in Zoom videoconferences","location":"Unspecified","documentation":{}},{"id":"1","tags":"Element,Software System,SistemaMonitoreo","name":"PractiFinder System","description":"Allows users to manage application tools","relationships":[{"id":"13","tags":"Relationship","sourceId":"1","destinationId":"3","description":"Uses Google Calendar event management service"},{"id":"15","tags":"Relationship","sourceId":"1","destinationId":"5","description":"Uses Google Firebase Authentication System"},{"id":"14","tags":"Relationship","sourceId":"1","destinationId":"4","description":"Uses Zoom videocoference service"},{"id":"12","tags":"Relationship","sourceId":"1","destinationId":"2","description":"Use API to make payments"}],"location":"Unspecified","containers":[{"id":"17","tags":"Element,Container,LandingPage","name":"Landing Page","technology":"React","documentation":{}},{"id":"16","tags":"Element,Container,WebApp","name":"Web Application","description":"Allows users to interact with PractiFinder Application","relationships":[{"id":"30","tags":"Relationship","sourceId":"16","destinationId":"18","description":"API Request","technology":"JSON/HTTPS"}],"technology":"PrimeVue UI","documentation":{}},{"id":"19","tags":"Element,Container,Database","name":"Database","documentation":{}},{"id":"21","tags":"Element,Container,Template,Context","name":"User Profile Context","description":"User authentication and profile data","relationships":[{"id":"38","tags":"Relationship","sourceId":"21","destinationId":"19"},{"id":"40","tags":"Relationship","sourceId":"21","destinationId":"5","description":"API Request","technology":"JSON/HTTPS"}],"components":[{"id":"71","tags":"Element,Component,Verify","name":"Employer Controller","description":"REST API endpoints","relationships":[{"id":"83","tags":"Relationship","sourceId":"71","destinationId":"75","description":"Uses"}],"documentation":{}},{"id":"72","tags":"Element,Component,AppointmentRepository","name":"Notificaction Controller","description":"Provides functionality to send notification via email to user","relationships":[{"id":"84","tags":"Relationship","sourceId":"72","destinationId":"73","description":"Uses"},{"id":"85","tags":"Relationship","sourceId":"72","destinationId":"76","description":"Uses"}],"documentation":{}},{"id":"76","tags":"Element,Component,NotifyComp","name":"Notification Component","description":"Sends and triggers  notification to user","relationships":[{"id":"87","tags":"Relationship","sourceId":"76","destinationId":"5","description":"JSON/HTTPS","technology":"[Sends notification to email]"},{"id":"90","tags":"Relationship","sourceId":"76","destinationId":"19"}],"documentation":{}},{"id":"74","tags":"Element,Component,MedicamentRepositor","name":"Security Component","description":"Provides functionality related to signing in, changing passwords, etc","relationships":[{"id":"88","tags":"Relationship","sourceId":"74","destinationId":"19"},{"id":"86","tags":"Relationship","sourceId":"74","destinationId":"5","description":"JSON/HTTPS"}],"documentation":{}},{"id":"70","tags":"Element,Component,TemplateApplicationService","name":"Student Controller","description":"REST API endpoints","relationships":[{"id":"82","tags":"Relationship","sourceId":"70","destinationId":"75","description":"Uses"}],"documentation":{}},{"id":"69","tags":"Element,Component,ControllerT","name":"User Profile Controller","description":"REST API endpoints","relationships":[{"id":"81","tags":"Relationship","sourceId":"69","destinationId":"74","description":"Uses"}],"documentation":{}},{"id":"75","tags":"Element,Component,FeatureComp","name":"Feature Component","description":"Allows users to use certain features","relationships":[{"id":"89","tags":"Relationship","sourceId":"75","destinationId":"19"}],"documentation":{}},{"id":"73","tags":"Element,Component,DomainLayer3","name":"Domain Layer","documentation":{}}],"documentation":{}},{"id":"23","tags":"Element,Container,SearchMedicCenter,Context","name":"Evaluation Context","description":"Evaluation management context","relationships":[{"id":"36","tags":"Relationship","sourceId":"23","destinationId":"19"}],"components":[{"id":"91","tags":"Element,Component,ControllerTT","name":"Revision Controller","description":"Provides evaluation revision and scoring","relationships":[{"id":"101","tags":"Relationship","sourceId":"91","destinationId":"95","description":"Uses"},{"id":"100","tags":"Relationship","sourceId":"91","destinationId":"94","description":"Uses"}],"technology":"REST API endpoints","documentation":{}},{"id":"93","tags":"Element,Component,Verifyy","name":"Evaluation Domain Layer","description":"REST API endpoints","documentation":{}},{"id":"94","tags":"Element,Component,AppointmentRepositoryy","name":"Answer Component","description":"Answer for tasks","relationships":[{"id":"102","tags":"Relationship","sourceId":"94","destinationId":"19"}],"documentation":{}},{"id":"95","tags":"Element,Component,DomainLayer4","name":"Task Component","description":"Evaluation tasks","relationships":[{"id":"103","tags":"Relationship","sourceId":"95","destinationId":"19"}],"documentation":{}},{"id":"92","tags":"Element,Component,TemplateApplicationServicee","name":"Evaluation Controller","description":"Provides evaluation creation and management","relationships":[{"id":"98","tags":"Relationship","sourceId":"92","destinationId":"93"},{"id":"99","tags":"Relationship","sourceId":"92","destinationId":"95","description":"Uses"}],"technology":"REST API endpoints","documentation":{}}],"documentation":{}},{"id":"20","tags":"Element,Container,BuyMedicaments,Context","name":"Payment Context","description":"Payment payment context","relationships":[{"id":"35","tags":"Relationship","sourceId":"20","destinationId":"19"},{"id":"43","tags":"Relationship","sourceId":"20","destinationId":"2","description":"API Request","technology":"JSON/HTTPS"}],"components":[{"id":"62","tags":"Element,Component,BuyApplicationService","name":"Payment Application Service","description":"Provides payment proccesing and validation methods","relationships":[{"id":"68","tags":"Relationship","sourceId":"62","destinationId":"19"},{"id":"66","tags":"Relationship","sourceId":"62","destinationId":"63","description":"Uses"}],"documentation":{}},{"id":"61","tags":"Element,Component,Controller","name":"Payment Controller","description":"REST API endpoints","relationships":[{"id":"65","tags":"Relationship","sourceId":"61","destinationId":"62","description":"Invoques payment proccesing methods"}],"technology":"REST controller","documentation":{}},{"id":"63","tags":"Element,Component,MetodosPagos","name":"Payment Facade","relationships":[{"id":"67","tags":"Relationship","sourceId":"63","destinationId":"2","description":"JSON/HTTPS"}],"documentation":{}}],"documentation":{}},{"id":"18","tags":"Element,Container,APIRest","name":"API RESTful","description":"API Rest","relationships":[{"id":"78","tags":"Relationship","sourceId":"18","destinationId":"70","technology":"JSON/HTTPS"},{"id":"80","tags":"Relationship","sourceId":"18","destinationId":"72","technology":"JSON/HTTPS"},{"id":"33","tags":"Relationship","sourceId":"18","destinationId":"22"},{"id":"50","tags":"Relationship","sourceId":"18","destinationId":"46","technology":"JSON/HTTPS"},{"id":"34","tags":"Relationship","sourceId":"18","destinationId":"21"},{"id":"96","tags":"Relationship","sourceId":"18","destinationId":"91","technology":"JSON/HTTPS"},{"id":"97","tags":"Relationship","sourceId":"18","destinationId":"92","technology":"JSON/HTTPS"},{"id":"31","tags":"Relationship","sourceId":"18","destinationId":"20"},{"id":"64","tags":"Relationship","sourceId":"18","destinationId":"61","technology":"JSON/HTTPS"},{"id":"77","tags":"Relationship","sourceId":"18","destinationId":"69","technology":"JSON/HTTPS"},{"id":"51","tags":"Relationship","sourceId":"18","destinationId":"45","technology":"JSON/HTTPS"},{"id":"32","tags":"Relationship","sourceId":"18","destinationId":"23"},{"id":"79","tags":"Relationship","sourceId":"18","destinationId":"71","technology":"JSON/HTTPS"}],"technology":"NodeJS","documentation":{}},{"id":"22","tags":"Element,Container,Appointment,Context","name":"Recruitment Context","description":"Recruitmen management context","relationships":[{"id":"41","tags":"Relationship","sourceId":"22","destinationId":"3","description":"API Request","technology":"JSON/HTTPS"},{"id":"42","tags":"Relationship","sourceId":"22","destinationId":"4","description":"API Request","technology":"JSON/HTTPS"},{"id":"39","tags":"Relationship","sourceId":"22","destinationId":"5","description":"API Request","technology":"JSON/HTTPS"},{"id":"37","tags":"Relationship","sourceId":"22","destinationId":"19"}],"components":[{"id":"44","tags":"Element,Component,DomainLayer","name":"Recruitment Domain Layer","documentation":{}},{"id":"49","tags":"Element,Component,CanC","name":"Candidate Component","relationships":[{"id":"57","tags":"Relationship","sourceId":"49","destinationId":"19"}],"documentation":{}},{"id":"45","tags":"Element,Component,MonitoringController","name":"Recruitment Controller","relationships":[{"id":"54","tags":"Relationship","sourceId":"45","destinationId":"48","description":"Uses"},{"id":"53","tags":"Relationship","sourceId":"45","destinationId":"49","description":"Uses"},{"id":"52","tags":"Relationship","sourceId":"45","destinationId":"44","description":"Uses"}],"technology":"REST API endpoints","documentation":{}},{"id":"48","tags":"Element,Component,EvaC","name":"Evaluation Component","relationships":[{"id":"58","tags":"Relationship","sourceId":"48","destinationId":"19"}],"technology":"REST API endpoints","documentation":{}},{"id":"47","tags":"Element,Component,FlightRepository","name":"Meeting Component","relationships":[{"id":"56","tags":"Relationship","sourceId":"47","destinationId":"19"},{"id":"60","tags":"Relationship","sourceId":"47","destinationId":"4","description":"JSON/HTTPS"},{"id":"59","tags":"Relationship","sourceId":"47","destinationId":"5","description":"JSON/HTTPS"}],"documentation":{}},{"id":"46","tags":"Element,Component,MonitoringApplicationService","name":"Conference Controller","relationships":[{"id":"55","tags":"Relationship","sourceId":"46","destinationId":"47","description":"Uses"}],"technology":"REST API endpoints","documentation":{}}],"documentation":{}}],"documentation":{}},{"id":"2","tags":"Element,Software System,Paypal","name":"PayPal Checkout System","description":"Allows users to make payments through Paypal third party application","location":"Unspecified","documentation":{}},{"id":"3","tags":"Element,Software System,Visa","name":"Google Calendar System","description":"Allows users to set reminders on their Google's account calendar","location":"Unspecified","documentation":{}}]},"documentation":{},"views":{"systemContextViews":[{"key":"Context","order":1,"description":"Context Diagram","softwareSystemId":"1","paperSize":"A4_Landscape","dimensions":{"width":3508,"height":2480},"enterpriseBoundaryVisible":true,"elements":[{"id":"1","x":0,"y":0},{"id":"2","x":420,"y":420},{"id":"3","x":1075,"y":245},{"id":"4","x":2495,"y":1790},{"id":"5","x":2045,"y":150},{"id":"6","x":2330,"y":275},{"id":"7","x":310,"y":965},{"id":"8","x":870,"y":1710}],"relationships":[{"id":"15"},{"id":"14"},{"id":"13"},{"id":"12"},{"id":"11"},{"id":"9"},{"id":"10"}]}],"containerViews":[{"key":"Container","order":1,"description":"Container Diagram","softwareSystemId":"1","externalSoftwareSystemBoundariesVisible":false,"elements":[{"id":"22","x":0,"y":0},{"id":"23","x":0,"y":0},{"id":"16","x":0,"y":0},{"id":"17","x":0,"y":0},{"id":"18","x":0,"y":0},{"id":"19","x":0,"y":0},{"id":"2","x":0,"y":0},{"id":"3","x":0,"y":0},{"id":"4","x":0,"y":0},{"id":"5","x":0,"y":0},{"id":"6","x":0,"y":0},{"id":"7","x":0,"y":0},{"id":"8","x":0,"y":0},{"id":"20","x":0,"y":0},{"id":"21","x":0,"y":0}],"relationships":[{"id":"40"},{"id":"41"},{"id":"42"},{"id":"43"},{"id":"32"},{"id":"31"},{"id":"30"},{"id":"29"},{"id":"28"},{"id":"27"},{"id":"26"},{"id":"37"},{"id":"25"},{"id":"36"},{"id":"24"},{"id":"35"},{"id":"34"},{"id":"33"},{"id":"38"},{"id":"39"}]}],"componentViews":[{"key":"Components","order":1,"description":"Components Chat","paperSize":"A4_Landscape","containerId":"22","externalContainerBoundariesVisible":false,"elements":[{"id":"44","x":0,"y":0},{"id":"45","x":0,"y":0},{"id":"46","x":0,"y":0},{"id":"47","x":0,"y":0},{"id":"4","x":0,"y":0},{"id":"48","x":0,"y":0},{"id":"16","x":0,"y":0},{"id":"5","x":0,"y":0},{"id":"49","x":0,"y":0},{"id":"18","x":0,"y":0},{"id":"19","x":0,"y":0}],"relationships":[{"id":"50"},{"id":"60"},{"id":"51"},{"id":"52"},{"id":"53"},{"id":"54"},{"id":"30"},{"id":"55"},{"id":"56"},{"id":"57"},{"id":"58"},{"id":"59"}]},{"key":"Componentss","order":1,"description":"Component Users","paperSize":"A4_Landscape","containerId":"21","externalContainerBoundariesVisible":false,"elements":[{"id":"69","x":0,"y":0},{"id":"16","x":0,"y":0},{"id":"18","x":0,"y":0},{"id":"19","x":0,"y":0},{"id":"5","x":0,"y":0},{"id":"70","x":0,"y":0},{"id":"71","x":0,"y":0},{"id":"72","x":0,"y":0},{"id":"73","x":0,"y":0},{"id":"74","x":0,"y":0},{"id":"75","x":0,"y":0},{"id":"76","x":0,"y":0}],"relationships":[{"id":"82"},{"id":"83"},{"id":"80"},{"id":"81"},{"id":"86"},{"id":"87"},{"id":"84"},{"id":"85"},{"id":"30"},{"id":"90"},{"id":"78"},{"id":"77"},{"id":"88"},{"id":"79"},{"id":"89"}]},{"key":"Component","order":1,"description":"Components Payments","paperSize":"A4_Landscape","containerId":"20","externalContainerBoundariesVisible":false,"elements":[{"id":"2","x":0,"y":0},{"id":"16","x":0,"y":0},{"id":"18","x":0,"y":0},{"id":"19","x":0,"y":0},{"id":"61","x":0,"y":0},{"id":"62","x":0,"y":0},{"id":"63","x":0,"y":0}],"relationships":[{"id":"65"},{"id":"64"},{"id":"67"},{"id":"66"},{"id":"30"},{"id":"68"}]},{"key":"Componenss","order":1,"description":"Component Accomodation Search","paperSize":"A4_Landscape","containerId":"23","externalContainerBoundariesVisible":false,"elements":[{"id":"16","x":0,"y":0},{"id":"18","x":0,"y":0},{"id":"19","x":0,"y":0},{"id":"91","x":0,"y":0},{"id":"92","x":0,"y":0},{"id":"93","x":0,"y":0},{"id":"94","x":0,"y":0},{"id":"95","x":0,"y":0}],"relationships":[{"id":"97"},{"id":"98"},{"id":"96"},{"id":"100"},{"id":"30"},{"id":"102"},{"id":"99"},{"id":"101"},{"id":"103"}]}],"configuration":{"branding":{},"styles":{"elements":[{"tag":"Paciente","background":"#0a60ff","color":"#ffffff","shape":"Person"},{"tag":"Admin","background":"#aa70af","color":"#ffffff","shape":"Person"},{"tag":"Doctor","background":"#aa20bf","color":"#ffffff","shape":"Person"},{"tag":"SistemaMonitoreo","background":"#008f39","color":"#ffffff","shape":"RoundedBox"},{"tag":"Paypal","background":"#60314c","color":"#ffffff","shape":"RoundedBox"},{"tag":"Visa","background":"#ff8c00","color":"#ffffff","shape":"RoundedBox"},{"tag":"Mastercard","background":"#8b0000","color":"#ffffff","shape":"RoundedBox"},{"tag":"DeliverySystem","background":"#4caf50","color":"#ffffff","shape":"RoundedBox"},{"tag":"WebApp","background":"#9d33d6","color":"#ffffff","shape":"WebBrowser"},{"tag":"LandingPage","background":"#929000","color":"#ffffff","shape":"WebBrowser"},{"tag":"APIRest","background":"#0000ff","color":"#ffffff","shape":"RoundedBox"},{"tag":"Database","background":"#ff0000","color":"#ffffff","shape":"Cylinder"},{"tag":"Context","background":"#facc2e","shape":"Hexagon"},{"tag":"DomainLayer","background":"#facc2e","shape":"Component"},{"tag":"EvaC","background":"#facc2e","shape":"Component"},{"tag":"CanC","background":"#facc2e","shape":"Component"},{"tag":"MonitoringController","background":"#facc2e","shape":"Component"},{"tag":"MonitoringApplicationService","background":"#facc2e","shape":"Component"},{"tag":"MonitoringDomainModel","background":"#facc2e","shape":"Component"},{"tag":"FlightStatus","background":"#facc2e","shape":"Component"},{"tag":"FlightRepository","background":"#facc2e","shape":"Component"},{"tag":"DomainLayer2","background":"#facc2e","shape":"Component"},{"tag":"Controller","background":"#facc2e","shape":"Component"},{"tag":"BuyApplicationService","background":"#facc2e","shape":"Component"},{"tag":"MetodosPagos","background":"#facc2e","shape":"Component"},{"tag":"DomainLayer3","background":"#facc2e","shape":"Component"},{"tag":"ControllerT","background":"#facc2e","shape":"Component"},{"tag":"TemplateApplicationService","background":"#facc2e","shape":"Component"},{"tag":"Verify","background":"#facc2e","shape":"Component"},{"tag":"AppointmentRepository","background":"#facc2e","shape":"Component"},{"tag":"MedicamentRepositor","background":"#facc2e","shape":"Component"},{"tag":"FeatureComp","background":"#facc2e","shape":"Component"},{"tag":"NotifyComp","background":"#facc2e","shape":"Component"},{"tag":"DomainLayer4","background":"#facc2e","shape":"Component"},{"tag":"ControllerTT","background":"#facc2e","shape":"Component"},{"tag":"TemplateApplicationServicee","background":"#facc2e","shape":"Component"},{"tag":"Verifyy","background":"#facc2e","shape":"Component"},{"tag":"AppointmentRepositoryy","background":"#facc2e","shape":"Component"}]},"terminology":{},"metadataSymbols":"SquareBrackets","lastSavedView":"Context","viewSortOrder":"Default"}}}